cliffcircular/__init__.py
cliffcircular/cliffcircular.py
cliffcircular/img/cookie.png
cliffcircular/img/elf_down.png
cliffcircular/img/elf_left.png
cliffcircular/img/elf_right.png
cliffcircular/img/elf_up.png
cliffcircular/img/mountain_bg1.png
cliffcircular/img/mountain_bg2.png
cliffcircular/img/mountain_cliff.png
cliffcircular/img/mountain_near-cliff1.png
cliffcircular/img/mountain_near-cliff2.png
cliffcircular/img/stool.png
cliffcircular-0.1.1.dist-info/LICENSE
cliffcircular-0.1.1.dist-info/METADATA
cliffcircular-0.1.1.dist-info/WHEEL
cliffcircular-0.1.1.dist-info/top_level.txt
cliffcircular-0.1.1.dist-info/RECORD
