Metadata-Version: 2.1
Name: cliffcircular
Version: 0.1.1
Summary: A custom Gymnasium gridworld environment for testing SafeRL algorithms for partially observable Constrained Submodular Markov Decision Processes
Home-page: https://github.com/EdisonPricehan/CliffCircular
Author: Zihan Wang
Author-email: wang5044@purdue.edu
License: GPLv3
Classifier: Development Status :: 3 - Alpha
Classifier: Intended Audience :: Developers
Classifier: Intended Audience :: Science/Research
Classifier: License :: OSI Approved :: GNU General Public License v3 (GPLv3)
Classifier: Programming Language :: Python :: 3
Classifier: Topic :: Software Development :: Libraries
Classifier: Topic :: Scientific/Engineering :: Artificial Intelligence
Classifier: Operating System :: OS Independent
Requires-Python: >=3.8
License-File: LICENSE
Requires-Dist: gymnasium>=0.26.0
Requires-Dist: numpy>=1.21.0
Requires-Dist: pygame>=2.0.0
